setup.py
irctest/__init__.py
irctest/__main__.py
irctest/authentication.py
irctest/basecontrollers.py
irctest/cases.py
irctest/client_mock.py
irctest/exceptions.py
irctest/runner.py
irctest/specifications.py
irctest/tls.py
irctest.egg-info/PKG-INFO
irctest.egg-info/SOURCES.txt
irctest.egg-info/dependency_links.txt
irctest.egg-info/requires.txt
irctest.egg-info/top_level.txt
irctest/client_tests/__init__.py
irctest/client_tests/test_cap.py
irctest/client_tests/test_sasl.py
irctest/client_tests/test_tls.py
irctest/controllers/__init__.py
irctest/controllers/charybdis.py
irctest/controllers/girc.py
irctest/controllers/hybrid.py
irctest/controllers/inspircd.py
irctest/controllers/limnoria.py
irctest/controllers/mammon.py
irctest/controllers/oragono.py
irctest/controllers/sopel.py
irctest/irc_utils/__init__.py
irctest/irc_utils/ambiguities.py
irctest/irc_utils/capabilities.py
irctest/irc_utils/message_parser.py
irctest/server_tests/__init__.py
irctest/server_tests/test_account_tag.py
irctest/server_tests/test_cap.py
irctest/server_tests/test_channel_operations.py
irctest/server_tests/test_connection_registration.py
irctest/server_tests/test_echo_message.py
irctest/server_tests/test_extended_join.py
irctest/server_tests/test_messages.py
irctest/server_tests/test_metadata.py
irctest/server_tests/test_monitor.py
irctest/server_tests/test_multi_prefix.py
irctest/server_tests/test_sasl.py
irctest/server_tests/test_starttls.py