Metadata-Version: 1.1
Name: irctest
Version: 0.1.2
Summary: A script to test interoperability of IRC software.
Home-page: https://github.com/ProgVal/irctest/
Author: Valentin Lorentz
Author-email: progval+irctest@progval.net
License: UNKNOWN
Platform: linux
Platform: linux2
Classifier: Development Status :: 2 - Pre-Alpha
Classifier: Environment :: Console
Classifier: Intended Audience :: Developers
Classifier: License :: OSI Approved :: MIT License
Classifier: Natural Language :: English
Classifier: Operating System :: POSIX
Classifier: Programming Language :: Python :: 3.2
Classifier: Programming Language :: Python :: 3.3
Classifier: Programming Language :: Python :: 3.4
Classifier: Programming Language :: Python :: 3.5
Classifier: Programming Language :: Python :: 3 :: Only
Classifier: Topic :: Communications :: Chat :: Internet Relay Chat
Classifier: Topic :: Software Development :: Testing
